{
  "feature": {
    "config": {
      "default": {
        "feature": "arboria:forest_oak/11",
        "placement": []
      },
      "features": [
        {
          "chance": 0.1,
          "feature": {
            "feature": "arboria:birch_bush/1",
            "placement": []
          }
        },
        {
          "chance": 0.2,
          "feature": {
            "feature": "arboria:oak_bush/2",
            "placement": []
          }
        },
        {
          "chance": 0.45,
          "feature": {
            "feature": "arboria:oak_bush/6",
            "placement": []
          }
        },
        {
          "chance": 0.15,
          "feature": {
            "feature": "arboria:oak_bush/7",
            "placement": []
          }
        },
        {
          "chance": 0.1,
          "feature": {
            "feature": "arboria:big_oak/3",
            "placement": []
          }
        },
        {
          "chance": 0.35,
          "feature": {
            "feature": "arboria:forest_oak/7",
            "placement": []
          }
        },
        {
          "chance": 0.5,
          "feature": {
            "feature": "arboria:forest_oak/9",
            "placement": []
          }
        }
      ]
    },
    "type": "minecraft:random_selector"
  },
  "placement": [
    {
      "count": 3,
      "type": "minecraft:count"
    },
    {
      "type": "minecraft:in_square"
    },
    {
      "noise_factor": 160.0,
      "noise_offset": -0.4,
      "noise_to_count_ratio": 1,
      "type": "minecraft:noise_based_count"
    },
    {
      "noise_factor": -160.0,
      "noise_offset": -0.4,
      "noise_to_count_ratio": 1,
      "type": "minecraft:noise_based_count"
    },
    {
      "heightmap": "MOTION_BLOCKING",
      "type": "minecraft:heightmap"
    },
    {
      "max_water_depth": 0,
      "type": "minecraft:surface_water_depth_filter"
    },
    {
      "type": "minecraft:biome"
    }
  ]
}