{
    "criteria": {
        "requirement": {
            "trigger": "minecraft:consume_item",
            "conditions": {
                "item": {
                    "items": "minecraft:compass",
                    "components": {
                        "minecraft:custom_model_data": {"floats": [724012]},
                        "minecraft:custom_data": {
                            "tool": "found_player"
                        }
                    }
                }
            }
        }
    },
    "rewards": {
        "function": "cursefight:tools/found_player/init"
    }
}
