{
    "pools": [
        {
            "rolls": 1,
            "entries": [
                {
                    "type": "item",
                    "name": "minecraft:cookie",
                    "functions": [
                        {
                            "function": "minecraft:set_components",
                            "components": {
                                "minecraft:item_name": { "translate": "item.jmmf.chocolate_doughnut"},
                                "minecraft:item_model": "jmmf:doughnut/chocolate_doughnut",
                                "minecraft:custom_data": {
                                    "smithed": { "id": "jmmf:chocolate_doughnut" },
                                    "joshmats": { "tag": ["doughnut"] }
                                },
                                "minecraft:food": {
                                    "nutrition": 3, "saturation": 3
                                }
                            }
                        }
                    ]
                }
            ]
        }
    ]
}
